{
  "assertions": [
    {
      "evidence": {
        "active_namespace": "personal",
        "active_tenant": "tenant_alpha",
        "approval_required": true,
        "audit_refs": [
          "audit_0017"
        ],
        "authenticated_principal": "principal_alice",
        "boundary": "local-only; production-not-ready; H02-H07 remain human-required",
        "egress_destination": "reports/network/vs2-egress-proof.json",
        "execution_result": "blocked_until_valid_approval",
        "policy_decision": {
          "audit_refs": [
            "audit_0017"
          ],
          "bundle_hash": "f16b6e6d952eb5f6a62b7d5ed98a4358327c8c63970e1f790ce590982425174d",
          "bundle_revision": "vs2-rego-local-v1",
          "decided_at_epoch": 1782045155,
          "decision": "deny",
          "decision_id": "policy_2a2e1d9b876b16e1",
          "evidence_refs": [],
          "input_digest": "2cbb1cb1dcf2b5f5c4a4a8fc3540dd7db4cbe8db24e51f87fad3dc7d36b9374b",
          "namespace_id": "personal",
          "policy_path": "cornerstone.vs2/deny",
          "reason_codes": [
            "high_risk_requires_approval"
          ],
          "resolution_path": [
            "Use trusted membership scope",
            "Request approval or required role",
            "Retry through governed path"
          ],
          "schema_version": "cs.policy_decision.vs2.v1",
          "tenant_id": "tenant_alpha",
          "trace_id": "trace_vs2_policy_local"
        },
        "risk": "high",
        "status": "passed",
        "ui_map": [
          "Home",
          "Search",
          "Artifacts",
          "Claims",
          "Actions",
          "Admin/Security"
        ]
      },
      "name": "r15_normal_user_navigation_stays_one_cornerstone_product",
      "passed": true
    },
    {
      "evidence": {
        "active_namespace": "personal",
        "active_tenant": "tenant_alpha",
        "approval_required": true,
        "audit_refs": [
          "audit_0017"
        ],
        "authenticated_principal": "principal_alice",
        "boundary": "local-only; production-not-ready; H02-H07 remain human-required",
        "egress_destination": "reports/network/vs2-egress-proof.json",
        "execution_result": "blocked_until_valid_approval",
        "policy_decision": {
          "audit_refs": [
            "audit_0017"
          ],
          "bundle_hash": "f16b6e6d952eb5f6a62b7d5ed98a4358327c8c63970e1f790ce590982425174d",
          "bundle_revision": "vs2-rego-local-v1",
          "decided_at_epoch": 1782045155,
          "decision": "deny",
          "decision_id": "policy_2a2e1d9b876b16e1",
          "evidence_refs": [],
          "input_digest": "2cbb1cb1dcf2b5f5c4a4a8fc3540dd7db4cbe8db24e51f87fad3dc7d36b9374b",
          "namespace_id": "personal",
          "policy_path": "cornerstone.vs2/deny",
          "reason_codes": [
            "high_risk_requires_approval"
          ],
          "resolution_path": [
            "Use trusted membership scope",
            "Request approval or required role",
            "Retry through governed path"
          ],
          "schema_version": "cs.policy_decision.vs2.v1",
          "tenant_id": "tenant_alpha",
          "trace_id": "trace_vs2_policy_local"
        },
        "risk": "high",
        "status": "passed",
        "ui_map": [
          "Home",
          "Search",
          "Artifacts",
          "Claims",
          "Actions",
          "Admin/Security"
        ]
      },
      "name": "r15_admin_security_detail_progressively_disclosed",
      "passed": true
    },
    {
      "evidence": {
        "forbidden_internal_labels": [
          "Archive Engine",
          "Connector Engine",
          "KnowledgeBase Engine",
          "Product Engine",
          "Provider Engine"
        ],
        "ui_map": [
          "Home",
          "Search",
          "Artifacts",
          "Claims",
          "Actions",
          "Admin/Security"
        ]
      },
      "name": "r15_internal_engine_names_not_required_in_navigation",
      "passed": true
    },
    {
      "evidence": {
        "secret_findings": 0
      },
      "name": "raw_dependencies_have_no_secret_findings",
      "passed": true
    }
  ],
  "evidence_commit": null,
  "expected_behavior": "Users still experience one CornerStone product; repo/engine names are not required mental models, while admin security detail remains available.",
  "given": "Policy, tenant, and connector controls are added.",
  "notes": "Scenario-specific validator executed against local synthetic users, tenants, policy, Postgres RLS, OPA, egress, audit, and regression evidence as applicable.",
  "observed_foundations": {
    "audit": "passed",
    "egress": "passed",
    "opa": "passed",
    "postgres": "passed",
    "regression": "passed"
  },
  "priority": "REGRESSION",
  "required_evidence": "UI map/screenshots, absence of required repo-name workflow.",
  "scenario_id": "VS2-SEC-R15",
  "schema_version": "cs.vs2.raw_scenario_evidence.v1",
  "source_commit": "7fea206f5f9e204612509334ebe511f13c148463",
  "source_tree": "c5c80e6d1e1949cbd1063e3ffc45cc87c0d591de",
  "then": "Users still experience one CornerStone product; repo/engine names are not required mental models, while admin security detail remains available.",
  "validator": "verify_vs2_sec_r15",
  "verification_command": [
    "cornerstone",
    "scenario",
    "verify",
    "vs2-policy-tenancy-egress",
    "--scenario",
    "VS2-SEC-R15",
    "--json"
  ],
  "verification_method": "Automated nav/DOM check plus human review in H06.",
  "when": "A normal user navigates the product."
}
