[{"endpoint":"/repos/owner/project-alpha/issues","method":"POST","operation":"issue.create","target":"github:repo:owner/project-alpha:issues"},{"endpoint":"/repos/owner/project-alpha/issues/1001/comments","method":"POST","operation":"issue.comment","target":"github:repo:owner/project-alpha:issue:1001:comments"},{"endpoint":"/repos/owner/project-alpha/issues/1001/labels","method":"POST","operation":"issue.label","target":"github:repo:owner/project-alpha:issue:1001:labels"},{"endpoint":"/repos/owner/project-alpha/contents/README.md","method":"PUT","operation":"file.write","target":"github:repo:owner/project-alpha:file:README.md"},{"endpoint":"/repos/owner/project-alpha/pulls/7/merge","method":"PUT","operation":"pull_request.merge","target":"github:repo:owner/project-alpha:pull:7:merge"},{"endpoint":"/repos/owner/project-alpha/git/refs","method":"POST","operation":"branch.create","target":"github:repo:owner/project-alpha:refs"},{"endpoint":"/repos/owner/project-alpha","method":"PATCH","operation":"repository.settings.update","target":"github:repo:owner/project-alpha:settings"},{"endpoint":"/repos/owner/project-alpha/issues/comments/1","method":"DELETE","operation":"issue.comment.delete","target":"github:repo:owner/project-alpha:comment:1"}]
